hcgk_kernel/__init__.py
hcgk_kernel/cli.py
hcgk_kernel-1.0.5.dist-info/licenses/LICENSE
hcgk_kernel-1.0.5.dist-info/METADATA
hcgk_kernel-1.0.5.dist-info/WHEEL
hcgk_kernel-1.0.5.dist-info/entry_points.txt
hcgk_kernel-1.0.5.dist-info/top_level.txt
hcgk_kernel-1.0.5.dist-info/RECORD
