Metadata-Version: 2.4
Name: hcgk-kernel
Version: 1.0.5
Summary: Hardware Control Gatekeeper Kernel - Authorization system for heavy AI models
Author-email: Matias Nisperuza <mnisperuza1102@gmail.com>
License: MIT
Project-URL: Homepage, https://github.com/mnisperuza/hcgk-kernels
Project-URL: Documentation, https://github.com/mnisperuza/hcgk-kernels#readme
Project-URL: Repository, https://github.com/mnisperuza/hcgk-kernels
Project-URL: Bug Tracker, https://github.com/mnisperuza/hcgk-kernels/issues
Keywords: hardware,gatekeeper,authorization,ai,models,gpu,vram,system-check,kernel
Classifier: Development Status :: 4 - Beta
Classifier: Intended Audience :: Developers
Classifier: License :: OSI Approved :: MIT License
Classifier: Programming Language :: Python :: 3
Classifier: Programming Language :: Python :: 3.8
Classifier: Programming Language :: Python :: 3.9
Classifier: Programming Language :: Python :: 3.10
Classifier: Programming Language :: Python :: 3.11
Classifier: Programming Language :: Python :: 3.12
Classifier: Topic :: Software Development :: Libraries :: Python Modules
Classifier: Topic :: System :: Hardware
Requires-Python: >=3.8
License-File: LICENSE
Requires-Dist: psutil>=5.9.0
Requires-Dist: torch>=2.0.0
Provides-Extra: dev
Requires-Dist: pytest>=7.0.0; extra == "dev"
Requires-Dist: pytest-cov>=4.0.0; extra == "dev"
Requires-Dist: black>=23.0.0; extra == "dev"
Requires-Dist: flake8>=6.0.0; extra == "dev"
Dynamic: license-file
